{
  "dock": {
    "id": "dock",
    "name": "Old Dock",
    "background": "assets/scenes/dock/background.webp",
    "hotspots": [
      {
        "id": "old_sign",
        "name": "Old Sign",
        "x": 20,
        "y": 40,
        "width": 10,
        "height": 15,
        "dialogue": "dock_sign"
      },
      {
        "id": "fuse_box",
        "name": "Rusty Fuse Box",
        "x": 65,
        "y": 45,
        "width": 8,
        "height": 12,
        "dialogue": "dock_fuse_box",
        "itemRequired": "rusty_fuse",
        "puzzleId": "power_station"
      },
      {
        "id": "signal_door",
        "name": "Locked Signal Door",
        "x": 80,
        "y": 30,
        "width": 12,
        "height": 40,
        "dialogue": "dock_door"
      }
    ]
  }
}
